lam/__init__.py
lam/core.py
lam/lam.py
lam/utils.py
lam/engines/__init__.py
lam/engines/base.py
lam/engines/javascript.py
lam/engines/jq.py
lam/engines/python.py
lam_cli-1.0.0.dist-info/licenses/LICENSE
lam_cli-1.0.0.dist-info/METADATA
lam_cli-1.0.0.dist-info/WHEEL
lam_cli-1.0.0.dist-info/entry_points.txt
lam_cli-1.0.0.dist-info/top_level.txt
lam_cli-1.0.0.dist-info/RECORD
