Metadata-Version: 2.4
Name: lam-cli
Version: 1.0.0
Summary: Secure data transformation tool supporting JQ and JavaScript (Bun)
Home-page: https://github.com/laminar-run/lam
Author: Laminar Run, Inc.
Author-email: connect@laminar.run
License: GPLv3
Project-URL: Documentation, https://docs.laminar.run
Project-URL: Source, https://github.com/laminar-run/lam
Project-URL: Issue Tracker, https://github.com/laminar-run/lam/issues
Keywords: laminar,api,integration,transformation,json,jq,javascript,bun
Classifier: Development Status :: 4 - Beta
Classifier: Environment :: Console
Classifier: Intended Audience :: Developers
Classifier: License :: OSI Approved :: GNU General Public License v3 (GPLv3)
Classifier: Operating System :: OS Independent
Classifier: Programming Language :: Python :: 3
Classifier: Programming Language :: Python :: 3.9
Classifier: Programming Language :: Python :: 3.10
Classifier: Programming Language :: Python :: 3.11
Classifier: Topic :: Software Development :: Libraries :: Python Modules
Classifier: Topic :: Internet :: WWW/HTTP :: Dynamic Content
Classifier: Topic :: Software Development :: Build Tools
Requires-Python: >=3.9
License-File: LICENSE
Requires-Dist: backoff>=2.2.1
Requires-Dist: certifi>=2024.12.14
Requires-Dist: charset-normalizer>=3.3.2
Requires-Dist: click>=8.1.7
Requires-Dist: idna>=3.7
Requires-Dist: logtail-python>=0.2.2
Requires-Dist: monotonic>=1.6
Requires-Dist: msgpack>=1.0.8
Requires-Dist: posthog>=3.4.0
Requires-Dist: psutil>=5.9.0
Requires-Dist: python-dateutil>=2.8.2
Requires-Dist: requests>=2.32.3
Requires-Dist: six>=1.16.0
Requires-Dist: urllib3>=2.2.2
Dynamic: author
Dynamic: author-email
Dynamic: classifier
Dynamic: description
Dynamic: description-content-type
Dynamic: home-page
Dynamic: keywords
Dynamic: license
Dynamic: license-file
Dynamic: project-url
Dynamic: requires-dist
Dynamic: requires-python
Dynamic: summary
